jpworkdays/__init__.py
jpworkdays/exception.py
jpworkdays/holiday.py
jpworkdays/jpworkdays.py
jpworkdays/registry.py
jpworkdays/utils.py
jpworkdays-0.2.0.data/data/README.md
jpworkdays-0.2.0.dist-info/LICENSE
jpworkdays-0.2.0.dist-info/METADATA
jpworkdays-0.2.0.dist-info/WHEEL
jpworkdays-0.2.0.dist-info/top_level.txt
jpworkdays-0.2.0.dist-info/RECORD
