Metadata-Version: 2.1
Name: jpworkdays
Version: 0.2.0
Summary: Generate Japan's Workdays Taking Account for Public Holidays
Home-page: https://github.com/discus0434/jp-workdays
Author: Kohei Ohno
Author-email: discus0434@gmail.com
License: MIT License
Keywords: Japan,Workdays
Platform: POSIX
Platform: Windows
Platform: Unix
Platform: MacOS
Classifier: Intended Audience :: Developers
Classifier: License :: OSI Approved :: MIT License
Classifier: Natural Language :: Japanese
Classifier: Operating System :: MacOS
Classifier: Operating System :: Microsoft
Classifier: Operating System :: POSIX
Classifier: Programming Language :: Python :: 3 :: Only
Classifier: Programming Language :: Python :: 3.7
Classifier: Programming Language :: Python :: 3.8
Classifier: Programming Language :: Python :: 3.9
Classifier: Programming Language :: Python :: 3.10
License-File: LICENSE
